csiphash/__init__.py
csiphash/_siphash.abi3.so
csiphash/six.py
csiphash-0.0.5.dist-info/DESCRIPTION.rst
csiphash-0.0.5.dist-info/METADATA
csiphash-0.0.5.dist-info/RECORD
csiphash-0.0.5.dist-info/WHEEL
csiphash-0.0.5.dist-info/metadata.json
csiphash-0.0.5.dist-info/top_level.txt
