Metadata-Version: 2.0
Name: csiphash
Version: 0.0.5
Summary: A CFFI-based implementation of SipHash24
Home-page: https://github.com/zacharyvoase/python-csiphash
Author: Zachary Voase
Author-email: zack@meat.io
License: UNLICENSE
Platform: UNKNOWN
Requires-Dist: cffi (>=1.4.0)
